{"id": 5, "width": 1920, "height": 1080, "duration": 21.0, "title": "Ed Sheeran - BLOW (with Chris Stapleton & Bruno Mars) [Official Music Video]", "user": "Ed Sheeran", "meta": {"description": "The official music video for Ed Sheeran - BLOW (with @chrisstapleton  & @brunomars)\nThe new album \"=\" is out now - listen here: https://es.lnk.to/equals\n \nTaken from No.6 Collaborations Project released in 2019, which featured the hit singles 'I Don't Care', 'Cross Me', 'Beautiful People', 'Blow', 'Best Part of Me', 'Antisocial', 'South of the Border' &'Take Me Back To London'. \n \nSubscribe to the Ed Sheeran channel for all the best and latest official music videos, behind the scenes and live performances.\u202f \nhttp://bit.ly/SubscribeToEdSheeran \n \nSee more official videos from Ed Sheeran here: \nhttps://www.youtube.com/watch?v=ryJgDL9jzKk&list=PLjp0AEEJ0-fGKG_3skl0e1FQlJfnx-TJz \n\nListen to more from the No. 6 Collaborations Project here : \nhttps://www.youtube.com/playlist?list=PLjp0AEEJ0-fHZDWhxhKo0wG08bMUcRy3l\n \nFollow Ed Sheeran on: \nFacebook: http://www.facebook.com/EdSheeranMusic  \nTwitter: http://twitter.com/edsheeran  \nInstagram: http://instagram.com/teddysphotos  \nOfficial Website: http://edsheeran.com  \n\nAbout Ed Sheeran: \nEd Sheeran\u202fmay be the quintessential pop star of the 2010s: an internationally acclaimed, multi-award winning singer/songwriter who seems to acknowledge no boundaries between styles or eras with elements of folk, hip-hop, pop, dance, soul, and rock woven throughout his music. \n\nHis incredible catalogue includes the studio albums \u2018+\u2019 (plus), \u2018x\u2019 (multiply) and \u2018\u00f7\u2019 (divide) which spawned hit singles such as \u2018The A team\u2019 , \u2019Lego House\u2019, \u2018Sing', \u2018Thinking Out Loud\u2019, \u2018Photograph\u2019, \u2018Shape Of You\u2019, \u2018Castle on The Hill\u2019 and \u2018Perfect\u2019. \n \nIn 2019, Ed Sheeran released the genre-spanning \u2018No.6 Collaborations Project\u2019 which featured a wide-range of artists including \u2018Justin Bieber\u2019, \u2018Camilla\u2019 Cabello\u2019, \u2018Travis Scott\u2019, \u2018Eminem\u2019, \u2018Cardi B, \u2018Paulo Londra\u2019, \u2018Bruno Mars\u2019 and \u2018Stormzy\u2019 amongst many others, producing hits such as \u2018I Don\u2019t Care\u2019, \u2018Beautiful People\u2019, \u2018South of The Border\u2019 and \u2018Take Me Back To London\u2019. \n \n#EdSheeran #ChrisStapleton #BrunoMars", "categories": ["Music"], "tags": ["Ed Sheeran", "Blow", "Chris Stapleton", "Bruno Mars", "Ed Sheeran Chris Stapleton Bruno Mars", "ed sheeran bruno mars", "ed sheeran chris stapleton", "Ed Sheeran Blow", "Ed Sheeran Official Video", "Blow Official Video", "Ed Sheeran music", "Ed Sheeran Lyrics", "Blow Lyrics", "Ed Sheeran 2019", "No. 6 Collaborations Project", "Ed Sheeran 4th album", "Ed Sheeran songs", "Pop", "Pop Music", "Ed", "Sheeran", "Ed Sheerin", "EdSheeran", "Ed Sheran", "English Songs", "English Song", "let me blow your mind"], "comments": [{"text": "\u2764\u2764\u2764\ud83c\udf89", "author": "mdmasummasum7385"}, {"text": "2024~2025:]?", "author": "\u06af\u0644\u0648\u062f\u064a\u0622"}, {"text": "I just discovered this song. In my feelings on the chris stapleton Playlist\ud83d\ude02\ud83d\ude02 and this song came on. I was super confused lol but it such a good song. I know I'm late but why wasn't this played more on the radio 5 yrs ago", "author": "tracytufts537"}, {"text": "love carrot top, glad his music career took off", "author": "TNUCampusStore"}, {"text": "I LOVE LOVE LOVE BRUNO, And LOVE LOVE LOVE ED but wasn't  expecting  this\ud83d\ude05", "author": "Justfunstuff4"}, {"text": "Great number, i love it\u2764", "author": "sabinealtmann3098"}, {"text": "ed bruno mars and chris all seem to be really good friends in here", "author": "hollypietrzak5214"}, {"text": "Ed Sheeran, nice content keep up the amazing content", "author": "IOSALive"}]}}